[
  {
    "id": 1,
    "brand": "MAZDA",
    "model": "CX-5",
    "year": 2014,
    "price": "Mk 48,000,000",
    "mileage": "76,000kms",
    "engine": "Skyactiv",
    "transmission": "Automatic",
    "fuel": "Petrol",
    "image": "/BIG5/assets/cars/10.webp",
    "description": "UNREGISTERED MAZDA CX-5 IN LILONGWE, just arrived (Duty paid)"
  },
  {
    "id": 2,
    "brand": "MAZDA",
    "model": "Axella",
    "year": 2018,
    "price": "Mk 32,000,000",
    "mileage": "105,000kms",
    "engine": "Skyactiv",
    "transmission": "Automatic",
    "fuel": "Petrol",
    "image": "/BIG5/assets/cars/13.webp",
    "description": "UNRESISTERED MAZDA AXELLA IN LILONGWE,  just arrived (Duty paid), very very smart machine"
  },
  {
    "id": 3,
    "brand": "MAZDA",
    "model": "CX-3",
    "year": 2015,
    "price": "Mk 35,000,000",
    "mileage": "75,000kms",
    "engine": "skyactiv",
    "transmission": "Automatic",
    "fuel": "Diesel",
    "image": "/BIG5/assets/cars/1.webp",
    "description": "Unregistered MAZDA CX-3 in Lilongwe, just arrived(Duty paid), very very smart machine"
  },
  {
    "id": 4,
    "brand": "BMW",
    "model": "X3",
    "year": 2019,
    "price": "MK 105,000,000",
    "mileage": "45,000kms",
    "engine": "Petrol Engine",
    "transmission": "Automatic",
    "fuel": "Petrol",
    "image": "/BIG5/assets/cars/car1.webp",
    "description": "UNREGISTERED BMW X3 IN LILONGWE, just arrived (Duty paid) very very smart machine."
  },
  {
    "id": 5,
    "brand": "TOYOTA",
    "model": "HIACE",
    "year": 2015,
    "price": "MK 65,000,000",
    "mileage": "78,000kms",
    "engine": "1TR ",
    "transmission": "Automatic",
    "fuel": "Petrol",
    "image": "/BIG5/assets/cars/11.webp",
    "description": "UNREGISTERED TOYOTA HIACE IN LILONGWE, just arrived ( Duty paid ) very very smart machine."
  },
  {
    "id": 6,
    "brand": "TOYOTA",
    "model": "FORTUNER",
    "year": 2022,
    "price": "MK 185,000,000",
    "mileage": "50,000kms",
    "engine": "GD6 2.4-Diesel",
    "transmission": "Automatic",
    "fuel": "Diesel",
    "image": "/BIG5/assets/cars/9.webp",
    "description": "UNREGISTERD TOYOTA FORTUNER IN LILONGWE, Ex -RSA Duty Fully Paid, Ver very smart machine"
  },
  {
    "id": 7,
    "brand": "FORD ",
    "model": "EVEREST XLT",
    "year": 2017,
    "price": "MK 137,000,000",
    "mileage": "87,000 kms",
    "engine": "3.2L Diesel",
    "transmission": "Automatic 4x4",
    "fuel": "Diesel",
    "image": "/BIG5/assets/cars/8.webp",
    "description": "UNREGISTERED FORD EVEREST XLT IN LILONGWE, EX_RSA Duty Fully paid, Mugrims/Extra Features, very very smart machine"
  }
]